README
setup.py
truss/__init__.py
truss/__main__.py
truss/core.py
truss/core_test.py
truss/markup.py
truss/truss.py
truss/truss_test.py
truss/files/__init__.py
truss/files/cert.pem
truss/files/favicon.ico
trussws.egg-info/PKG-INFO
trussws.egg-info/SOURCES.txt
trussws.egg-info/dependency_links.txt
trussws.egg-info/entry_points.txt
trussws.egg-info/top_level.txt